guarddog/__init__.py
guarddog/__main__.py
guarddog/analyzer/__init__.py
guarddog/analyzer/analyzer.py
guarddog/analyzer/metadata/__init__.py
guarddog/analyzer/metadata/bundled_binary.py
guarddog/analyzer/metadata/deceptive_author.py
guarddog/analyzer/metadata/detector.py
guarddog/analyzer/metadata/empty_information.py
guarddog/analyzer/metadata/github_action/__init__.py
guarddog/analyzer/metadata/go/__init__.py
guarddog/analyzer/metadata/go/typosquatting.py
guarddog/analyzer/metadata/npm/__init__.py
guarddog/analyzer/metadata/npm/bundled_binary.py
guarddog/analyzer/metadata/npm/deceptive_author.py
guarddog/analyzer/metadata/npm/direct_url_dependency.py
guarddog/analyzer/metadata/npm/empty_information.py
guarddog/analyzer/metadata/npm/npm_metadata_mismatch.py
guarddog/analyzer/metadata/npm/potentially_compromised_email_domain.py
guarddog/analyzer/metadata/npm/release_zero.py
guarddog/analyzer/metadata/npm/typosquatting.py
guarddog/analyzer/metadata/npm/unclaimed_maintainer_email_domain.py
guarddog/analyzer/metadata/npm/utils.py
guarddog/analyzer/metadata/potentially_compromised_email_domain.py
guarddog/analyzer/metadata/pypi/__init__.py
guarddog/analyzer/metadata/pypi/bundled_binary.py
guarddog/analyzer/metadata/pypi/deceptive_author.py
guarddog/analyzer/metadata/pypi/empty_information.py
guarddog/analyzer/metadata/pypi/potentially_compromised_email_domain.py
guarddog/analyzer/metadata/pypi/release_zero.py
guarddog/analyzer/metadata/pypi/repository_integrity_mismatch.py
guarddog/analyzer/metadata/pypi/single_python_file.py
guarddog/analyzer/metadata/pypi/typosquatting.py
guarddog/analyzer/metadata/pypi/unclaimed_maintainer_email_domain.py
guarddog/analyzer/metadata/pypi/utils.py
guarddog/analyzer/metadata/release_zero.py
guarddog/analyzer/metadata/repository_integrity_mismatch.py
guarddog/analyzer/metadata/resources/placeholder_email_domains.txt
guarddog/analyzer/metadata/resources/top_go_packages.json
guarddog/analyzer/metadata/resources/top_npm_packages.json
guarddog-2.8.4.dist-info/METADATA
guarddog-2.8.4.dist-info/WHEEL
guarddog-2.8.4.dist-info/entry_points.txt
guarddog-2.8.4.dist-info/licenses/LICENSE
guarddog-2.8.4.dist-info/licenses/LICENSE-3rdparty.csv
guarddog-2.8.4.dist-info/licenses/NOTICE
guarddog-2.8.4.dist-info/RECORD
